Anshul/__init__.py
Anshul/main.py
anshul-1.0.1.dist-info/METADATA
anshul-1.0.1.dist-info/WHEEL
anshul-1.0.1.dist-info/entry_points.txt
anshul-1.0.1.dist-info/top_level.txt
anshul-1.0.1.dist-info/RECORD
