Metadata-Version: 2.4
Name: Anshul
Version: 1.0.1
Summary: A YouTube & Spotify downloader with auto-setup and updates.
Author: Anshul Dubey
Author-email: anshul@example.com
Requires-Python: >=3.6
Requires-Dist: yt-dlp
Requires-Dist: spotdl
Dynamic: author
Dynamic: author-email
Dynamic: description
Dynamic: description-content-type
Dynamic: requires-dist
Dynamic: requires-python
Dynamic: summary
